deepdlncud/__init__.py
deepdlncud/predict.py
deepdlncud/util/Biochar.py
deepdlncud/util/Console.py
deepdlncud/util/Feature.py
deepdlncud/util/Model.py
deepdlncud/util/__init__.py
deepdlncud-0.0.1.dist-info/METADATA
deepdlncud-0.0.1.dist-info/WHEEL
deepdlncud-0.0.1.dist-info/entry_points.txt
deepdlncud-0.0.1.dist-info/RECORD
