Metadata-Version: 2.3
Name: deepdlncud
Version: 0.0.1
Summary: 
License: GPL-3.0
Author: Jianfeng Sun
Author-email: jianfeng.sunmt@gmail.com
Requires-Python: >=3.11,<3.12
Classifier: License :: OSI Approved :: GNU General Public License v3 (GPLv3)
Classifier: Programming Language :: Python :: 3
Classifier: Programming Language :: Python :: 3.11
Requires-Dist: biopython (>=1.85,<2.0)
Requires-Dist: click (>=8.1.8,<9.0.0)
Requires-Dist: numpy (==1.24.3)
Requires-Dist: pandas (>=2.2.3,<3.0.0)
Requires-Dist: pyfiglet (>=1.0.2,<2.0.0)
Requires-Dist: rdkit (>=2024.9.6,<2025.0.0)
Requires-Dist: tensorflow (==2.14)
Requires-Dist: tensorflow-io-gcs-filesystem (==0.31.0)
